[
  {
    "id": 1,
    "calendar_number": 2,
    "min_age": "18+",
    "plan_type": "scale",
    "title": "Warm Weather",
    "description": "With its 24 ° C you are going to challenge yourself to the imposing mountains and crossings of Quindío, enjoying a delicious Colombian coffee and sweet fruits from the area.",
    "base_price": "24-30 °C",
    "stars": 9,
    "opinions": "Good",
    "img": "https://enbici.s3.us-east-2.amazonaws.com/images/clima-calido.jpg"
  },
  {
    "id": 2,
    "calendar_number": 2,
    "min_age": "18+",
    "plan_type": "plano",
    "title": "Mild Weather",
    "description": "It is the perfect climate for you to enjoy the ride through small and large mountains, some routes will make you improve and challenge yourself.",
    "base_price": "15-27 °C",
    "stars": 8,
    "opinions": "Good",
    "img": "https://enbici.s3.us-east-2.amazonaws.com/images/clima-templado.jpg"
  },
  {
    "id": 3,
    "calendar_number": 2,
    "min_age": "18+",
    "plan_type": "scale",
    "title": "Cold Weather",
    "description": "You will ride over 3440 MSNM, enjoy the stops, lagoons and cultures. Where you will meet from the salt mine of Zipaquirá, to monserrate in Bogotá.",
    "base_price": "12-25 °C",
    "stars": 9,
    "opinions": "Good",
    "img": "https://enbici.s3.us-east-2.amazonaws.com/images/clima-frio.jpg"
  },
  {
    "id": 4,
    "calendar_number": 6,
    "min_age": "18+",
    "plan_type": "scale",
    "title": "Warm Weather",
    "description": "With 31 ° C you can ride your bike between rivers, ravines, deserts like tatacoa and the longest port in the world: EL ALTO DE LETRAS, you will also measure your resistance and your physical condition.",
    "base_price": "31-38 °C",
    "stars": "9.5+",
    "opinions": "Good",
    "img": "https://enbici.s3.us-east-2.amazonaws.com/images/clima-caliente.jpg"
  }
]
